treadmill_sdk-0.1.6.dist-info/METADATA
treadmill_sdk-0.1.6.dist-info/WHEEL
treadmill_sdk-0.1.6.dist-info/licenses/LICENSE
treadmill_sdk/__init__.py
treadmill_sdk/__init__.pyi
treadmill_sdk/py.typed
treadmill_sdk/treadmill_sdk.abi3.so
treadmill_sdk-0.1.6.dist-info/RECORD
