Metadata-Version: 2.4
Name: treadmill_sdk
Version: 0.1.6
Classifier: Programming Language :: Rust
Classifier: Programming Language :: Python :: Implementation :: CPython
Classifier: Programming Language :: Python :: Implementation :: PyPy
License-File: LICENSE
Summary: BrainCo Treadmill SDK
Author: BrainCo
License: 	
Requires-Python: >=3.8
Project-URL: Source Code, https://github.com/BrainCoTech/treadmill-sdk
